sphinxcontrib_nicovideo-0.1.1-py2.7-nspkg.pth
sphinxcontrib/nicovideo.py
sphinxcontrib_nicovideo-0.1.1.dist-info/DESCRIPTION.rst
sphinxcontrib_nicovideo-0.1.1.dist-info/METADATA
sphinxcontrib_nicovideo-0.1.1.dist-info/RECORD
sphinxcontrib_nicovideo-0.1.1.dist-info/WHEEL
sphinxcontrib_nicovideo-0.1.1.dist-info/metadata.json
sphinxcontrib_nicovideo-0.1.1.dist-info/namespace_packages.txt
sphinxcontrib_nicovideo-0.1.1.dist-info/top_level.txt
