Metadata-Version: 2.0
Name: sphinxcontrib-nicovideo
Version: 0.1.1
Summary: Sphinx "nicovideo" extension
Home-page: http://bitbucket.org/birkenfeld/sphinx-contrib
Author: Takeshi KOMIYA
Author-email: i.tkomiya@gmail.com
License: BSD
Download-URL: http://pypi.python.org/pypi/sphinxcontrib-nicovideo
Platform: any
Classifier: Development Status :: 4 - Beta
Classifier: Environment :: Console
Classifier: Environment :: Web Environment
Classifier: Framework :: Sphinx :: Extension
Classifier: Intended Audience :: Developers
Classifier: License :: OSI Approved :: BSD License
Classifier: Operating System :: OS Independent
Classifier: Programming Language :: Python
Classifier: Programming Language :: Python :: 2.6
Classifier: Programming Language :: Python :: 2.7
Classifier: Programming Language :: Python :: 3.2
Classifier: Programming Language :: Python :: 3.3
Classifier: Topic :: Documentation
Classifier: Topic :: Documentation :: Sphinx
Classifier: Topic :: Utilities
Requires-Dist: Sphinx (>=0.6)
Requires-Dist: setuptools
